py_random_words/__init__.py
py_random_words/animals.json
py_random_words/random_words.py
py_random_words-0.8.0.data/data/animals.json/animals.json
py_random_words-0.8.0.dist-info/LICENSE
py_random_words-0.8.0.dist-info/METADATA
py_random_words-0.8.0.dist-info/WHEEL
py_random_words-0.8.0.dist-info/top_level.txt
py_random_words-0.8.0.dist-info/RECORD
