Metadata-Version: 2.1
Name: py_random_words
Version: 0.8.0
Summary: Generate random names
Home-page: https://github.com/andreasonny83/py_random_words
Author: andreasonny83
Author-email: andreasonny83@gmail.com
License: MIT
Platform: UNKNOWN
